fermifunctions/__init__.py
fermifunctions-0.0.1.dist-info/DESCRIPTION.rst
fermifunctions-0.0.1.dist-info/METADATA
fermifunctions-0.0.1.dist-info/RECORD
fermifunctions-0.0.1.dist-info/WHEEL
fermifunctions-0.0.1.dist-info/metadata.json
fermifunctions-0.0.1.dist-info/top_level.txt
