Metadata-Version: 2.0
Name: fermifunctions
Version: 0.0.1
Summary: UNKNOWN
Home-page: UNKNOWN
Author: Parth Patel
Author-email: ranchop@gmail.com
License: Open Source
Platform: UNKNOWN
Requires-Dist: numpy
